gaidme/.DS_Store
gaidme/__init__.py
gaidme/_version.py
gaidme/api_client.py
gaidme/cli.py
gaidme/command_manager.py
gaidme/commands/.DS_Store
gaidme/commands/__init__.py
gaidme/commands/ask.py
gaidme/commands/help.py
gaidme/commands/quit.py
gaidme/commands/settings.py
gaidme/compiler.py
gaidme/config_manager.py
gaidme/exceptions.py
gaidme/history_manager.py
gaidme/io.py
gaidme/logger.py
gaidme/models.py
gaidme/theme.py
gaidme/utils.py
gaidme-1.0.0.dist-info/LICENSE.txt
gaidme-1.0.0.dist-info/METADATA
gaidme-1.0.0.dist-info/WHEEL
gaidme-1.0.0.dist-info/entry_points.txt
gaidme-1.0.0.dist-info/RECORD
