Metadata-Version: 2.1
Name: gaidme
Version: 1.0.0
Summary: cool AI-powered CLI tool
Home-page: https://github.com/mateusztylec/gaidme
License: Proprietary
Author: Mateusz Tylec
Author-email: hi@gaidme.app
Requires-Python: >=3.8,<4.0
Classifier: License :: Other/Proprietary License
Classifier: Programming Language :: Python :: 3
Classifier: Programming Language :: Python :: 3.8
Classifier: Programming Language :: Python :: 3.9
Classifier: Programming Language :: Python :: 3.10
Classifier: Programming Language :: Python :: 3.11
Classifier: Programming Language :: Python :: 3.12
Requires-Dist: colorlog (>=6.8.2,<7.0.0)
Requires-Dist: openai (>=1.9.0,<2.0.0)
Requires-Dist: pexpect (>=4.9.0,<5.0.0)
Requires-Dist: pydantic (>=2.6.1,<3.0.0)
Requires-Dist: pygments (>=2.18.0,<3.0.0)
Requires-Dist: pyperclip (>=1.9.0,<2.0.0)
Requires-Dist: python-dotenv (>=1.0.1,<2.0.0)
Requires-Dist: questionary (>=2.0.1,<3.0.0)
Requires-Dist: requests (>=2.32.3,<3.0.0)
Requires-Dist: rich (>=13.7.1,<14.0.0)
Requires-Dist: shellingham (>=1.5.4,<2.0.0)
Project-URL: Repository, https://github.com/mateusztylec/gaidme
